modularml/__init__.py
modularml/core/__init__.py
modularml/core/data_structures/__init__.py
modularml/core/data_structures/batch.py
modularml/core/data_structures/data.py
modularml/core/data_structures/feature_set.py
modularml/core/data_structures/feature_subset.py
modularml/core/data_structures/sample.py
modularml/core/data_structures/sample_collection.py
modularml/core/experiment/__init__.py
modularml/core/experiment/base_phase.py
modularml/core/experiment/eval_phase.py
modularml/core/experiment/experiment.py
modularml/core/experiment/training_phase.py
modularml/core/feature_transforms/__init__.py
modularml/core/feature_transforms/feature_transform.py
modularml/core/model_graph/__init__.py
modularml/core/model_graph/activation.py
modularml/core/model_graph/loss.py
modularml/core/model_graph/model_graph.py
modularml/core/model_graph/model_stage.py
modularml/core/model_graph/optimizer.py
modularml/core/samplers/__init__.py
modularml/core/samplers/feature_sampler.py
modularml/core/splitters/__init__.py
modularml/core/splitters/conditon_splitter.py
modularml/core/splitters/random_splitter.py
modularml/core/splitters/splitter.py
modularml/models/__init__.py
modularml/models/base.py
modularml/models/combinators.py
modularml/models/sequential.py
modularml/preprocessing/__init__.py
modularml/preprocessing/absolute.py
modularml/preprocessing/negate.py
modularml/preprocessing/per_sample_min_max.py
modularml/preprocessing/per_sample_zero.py
modularml/preprocessing/segmented_scaler.py
modularml/utils/__init__.py
modularml/utils/backend.py
modularml/utils/data_format.py
modularml/utils/exceptions.py
modularml-0.1.3.dist-info/licenses/LICENSE
modularml-0.1.3.dist-info/METADATA
modularml-0.1.3.dist-info/WHEEL
modularml-0.1.3.dist-info/top_level.txt
modularml-0.1.3.dist-info/RECORD
