Metadata-Version: 2.4
Name: ModularML
Version: 0.1.3
Summary: A library for modular, fast, and reproducible ML experimentation built for R&D.
Author-email: Benjamin Nowacki <benjamin.nowacki@uconn.edu>, Tingkai Li <tingkai.li@uconn.edu>, Chao Hu <chao.hu@uconn.edu>
License-Expression: Apache-2.0
Project-URL: Homepage, https://github.com/REIL-UConn/modular-ml
Project-URL: Repository, https://github.com/REIL-UConn/modular-ml
Project-URL: Issues, https://github.com/REIL-UConn/modular-ml/issues
Keywords: Machine learning,Deep learning,Reproducible research,Neural networks,Scientific computing,Scientific machine learning
Classifier: Development Status :: 3 - Alpha
Classifier: Intended Audience :: Science/Research
Classifier: Topic :: Scientific/Engineering
Classifier: Topic :: Scientific/Engineering :: Artificial Intelligence
Classifier: Programming Language :: Python
Requires-Python: >=3.9
License-File: LICENSE
Requires-Dist: numpy
Requires-Dist: scipy
Requires-Dist: pandas
Requires-Dist: scikit-learn
Requires-Dist: scikit-optimize>=0.9.0
Requires-Dist: optuna
Requires-Dist: torch
Requires-Dist: tensorflow
Requires-Dist: networkx
Requires-Dist: plotly
Requires-Dist: matplotlib
Requires-Dist: nbformat
Requires-Dist: joblib
Dynamic: license-file
